loggerplus/__init__.py
loggerplus/__main__.py
pykotor/__init__.py
pykotor/common/__init__.py
pykotor/common/alien_sounds.py
pykotor/common/game_object.py
pykotor/common/geometry_utils.py
pykotor/common/indoorkit.py
pykotor/common/indoormap.py
pykotor/common/language.py
pykotor/common/misc.py
pykotor/common/module.py
pykotor/common/module_loader.py
pykotor/common/modulekit.py
pykotor/common/pathfinding.py
pykotor/common/script.py
pykotor/common/scriptdefs.py
pykotor/common/scriptlib.py
pykotor/common/stream.py
pykotor/engine/__init__.py
pykotor/engine/core.py
pykotor/engine/animation/__init__.py
pykotor/engine/animation/base.py
pykotor/engine/graphics/__init__.py
pykotor/engine/graphics/gui.py
pykotor/engine/materials/__init__.py
pykotor/engine/materials/base.py
pykotor/engine/panda3d/__init__.py
pykotor/engine/panda3d/animation.py
pykotor/engine/panda3d/engine.py
pykotor/engine/panda3d/mdl_loader.py
pykotor/engine/panda3d/module_loader.py
pykotor/engine/panda3d/scene_graph.py
pykotor/engine/panda3d/legacy/__init__.py
pykotor/engine/panda3d/legacy/__main__.py
pykotor/engine/panda3d/legacy/loader.py
pykotor/engine/panda3d/legacy/scene.py
pykotor/engine/panda3d/materials/__init__.py
pykotor/engine/panda3d/materials/manager.py
pykotor/engine/panda3d/resources/__init__.py
pykotor/engine/panda3d/resources/texture_loader.py
pykotor/engine/scene/__init__.py
pykotor/engine/scene/base.py
pykotor/extract/__init__.py
pykotor/extract/bzf.py
pykotor/extract/capsule.py
pykotor/extract/chitin.py
pykotor/extract/file.py
pykotor/extract/installation.py
pykotor/extract/keyfile.py
pykotor/extract/keywriter.py
pykotor/extract/savedata.py
pykotor/extract/talktable.py
pykotor/extract/twoda.py
pykotor/font/__init__.py
pykotor/font/draw.py
pykotor/font/grid.py
pykotor/font/metrics.py
pykotor/gl/__init__.py
pykotor/gl/compat.py
pykotor/gl/glm_compat.py
pykotor/gl/models/__init__.py
pykotor/gl/models/boundary.py
pykotor/gl/models/cube.py
pykotor/gl/models/empty.py
pykotor/gl/models/mdl.py
pykotor-2.0.5.dist-info/licenses/LICENSE
pykotor-2.0.5.dist-info/METADATA
pykotor-2.0.5.dist-info/WHEEL
pykotor-2.0.5.dist-info/top_level.txt
pykotor-2.0.5.dist-info/RECORD
